README.md
setup.py
tests/__init__.py
tests/run.py
tests/test_initial.py
tunner/__init__.py
tunner.egg-info/PKG-INFO
tunner.egg-info/SOURCES.txt
tunner.egg-info/dependency_links.txt
tunner.egg-info/entry_points.txt
tunner.egg-info/requires.txt
tunner.egg-info/top_level.txt
tunner/configuration/cp.json
tunner/configuration/starter.json
tunner/gui/__init__.py
tunner/gui/starter.py
tunner/gui/starter_widgets.py